dy05/__init__.py
dy05/__main__.py
dy05/dy05.py
solight_dy05-1.0.0.dist-info/METADATA
solight_dy05-1.0.0.dist-info/WHEEL
solight_dy05-1.0.0.dist-info/entry_points.txt
solight_dy05-1.0.0.dist-info/top_level.txt
solight_dy05-1.0.0.dist-info/RECORD
