Metadata-Version: 2.1
Name: solight-dy05
Version: 1.0.0
Summary: Control Solight DY05 sockets
Home-page: https://github.com/Funcoil/SolightDY05-PythonRpi
Author: Martin Habovstiak
Author-email: martin.habovstiak@gmail.com
License: MIT
Platform: UNKNOWN
Classifier: License :: OSI Approved :: MIT License
Classifier: Programming Language :: Python :: 3
Classifier: Topic :: Home Automation
Classifier: Operating System :: POSIX :: Linux
Requires-Dist: pigpio
